python_otbr_api/__init__.py
python_otbr_api/mdns.py
python_otbr_api/models.py
python_otbr_api/pskc.py
python_otbr_api/py.typed
python_otbr_api/tlv_parser.py
python_otbr_api-2.7.1.dist-info/licenses/LICENSE
python_otbr_api-2.7.1.dist-info/METADATA
python_otbr_api-2.7.1.dist-info/WHEEL
python_otbr_api-2.7.1.dist-info/top_level.txt
python_otbr_api-2.7.1.dist-info/zip-safe
python_otbr_api-2.7.1.dist-info/RECORD
