Metadata-Version: 2.4
Name: python-otbr-api
Version: 2.7.1
Summary: API to interact with an OTBR via its REST API
Author-email: The Home Assistant Authors <hello@home-assistant.io>
License: MIT
Project-URL: Homepage, https://github.com/home-assistant-libs/python-otbr-api
Platform: any
Requires-Python: >=3.9.0
License-File: LICENSE
Requires-Dist: aiohttp
Requires-Dist: bitstruct
Requires-Dist: cryptography
Requires-Dist: typing_extensions
Requires-Dist: voluptuous
Dynamic: license-file
